django_18_fast_migrations/__init__.py
django_18_fast_migrations/apps.py
django_18_fast_migrations/migration_executor_patched.py
django_18_fast_migrations/management/__init__.py
django_18_fast_migrations/management/commands/__init__.py
django_18_fast_migrations/management/commands/migrate.py
django_18_fast_migrations-0.1.1.dist-info/DESCRIPTION.rst
django_18_fast_migrations-0.1.1.dist-info/METADATA
django_18_fast_migrations-0.1.1.dist-info/RECORD
django_18_fast_migrations-0.1.1.dist-info/WHEEL
django_18_fast_migrations-0.1.1.dist-info/metadata.json
django_18_fast_migrations-0.1.1.dist-info/top_level.txt
