Metadata-Version: 2.0
Name: django-18-fast-migrations
Version: 0.1.1
Summary: Fast migrations from Django 1.10 backported into Django 1.8
Home-page: https://github.com/shaib/django_18_fast_migrations
Author: Shai Berger
Author-email: shai@platonix.com
License: BSD
Keywords: django_18_fast_migrations
Platform: UNKNOWN
Classifier: Development Status :: 3 - Alpha
Classifier: Framework :: Django
Classifier: Framework :: Django :: 1.8
Classifier: Intended Audience :: Developers
Classifier: License :: OSI Approved :: BSD License
Classifier: Natural Language :: English
Classifier: Programming Language :: Python :: 2
Classifier: Programming Language :: Python :: 2.7
Classifier: Programming Language :: Python :: 3
Classifier: Programming Language :: Python :: 3.3
Classifier: Programming Language :: Python :: 3.4
Classifier: Programming Language :: Python :: 3.5
